[{"hostname":"VPN126672345.OPENGW.NET","ip":"119.230.209.5","port":1782,"info":"0 SESSIONS 3 DAYS TOTAL 868,364 USERS","info2":"ASIA 96.32","location":{"country":"JAPAN","short":"JP","name":"OPTAGE INC"},"createdAt":"2022-09-20T00:33:58.128Z","id":"1010576"},{"hostname":"VPN280763047.OPENGW.NET","ip":"121.112.60.239","port":1759,"info":"9 SESSIONS 0 MINS TOTAL 75,825 USERS","info2":"ASIA 273.69","location":{"country":"JAPAN","short":"JP","name":"NTT COMMUNICATIONS CORPORATION"},"createdAt":"2022-09-20T00:33:58.130Z","id":"0649275"},{"hostname":"VPN946942580.OPENGW.NET","ip":"118.173.112.232","port":1404,"info":"0 SESSIONS 12 HOURS TOTAL 21,628 USERS","info2":"ASIA 191.43","location":{"country":"THAILAND","short":"TH","name":"TOT PUBLIC COMPANY LIMITED"},"createdAt":"2022-09-20T00:33:58.131Z","id":"0613438"},{"hostname":"VPN797519971.OPENGW.NET","ip":"123.50.64.145","port":443,"info":"0 SESSIONS 18 HOURS TOTAL 22,241 USERS","info2":"OCEANIA 51.98","location":{"country":"FRENCH POLYNESIA","short":"PF","name":"ONATI"},"createdAt":"2022-09-20T00:33:58.133Z","id":"0577576"},{"hostname":"VPN367600361.OPENGW.NET","ip":"103.216.50.37","port":1223,"info":"1 SESSIONS 3 HOURS TOTAL 0 USERS","info2":"ASIA 19.63","location":{"country":"CAMBODIA","short":"KH","name":"TODAY COMMUNICATION CO LTD"},"createdAt":"2022-09-20T00:33:58.133Z","id":"0521245"},{"hostname":"VPN561795455.OPENGW.NET","ip":"137.125.129.43","port":995,"info":"0 SESSIONS 0 MINS TOTAL 0 USERS","info2":"NORTH AMERICA 59.19","location":{"country":"UNITED STATES","short":"US","name":"FARMINGDALESTATE"},"createdAt":"2022-09-20T00:33:58.134Z","id":"0481379"},{"hostname":"VPN835954596.OPENGW.NET","ip":"125.0.190.244","port":1781,"info":"0 SESSIONS 12 HOURS TOTAL 226,144 USERS","info2":"ASIA 10.25","location":{"country":"JAPAN","short":"JP","name":"FUJITSU LIMITED"},"createdAt":"2022-09-20T00:33:58.134Z","id":"0422759"},{"hostname":"VPN108485795.OPENGW.NET","ip":"83.216.110.225","port":1630,"info":"0 SESSIONS 0 MINS TOTAL 1,703 USERS","info2":"EUROPE 56.55","location":{"country":"SWEDEN","short":"SE","name":"SANDVIKEN ENERGI AB"},"createdAt":"2022-09-20T00:33:58.134Z","id":"0387282"},{"hostname":"VPN286449167.OPENGW.NET","ip":"45.14.25.145","port":1863,"info":"0 SESSIONS 3 HOURS TOTAL 84 USERS","info2":"EUROPE 9.64","location":{"country":"UKRAINE","short":"UA","name":"EVEREST TV AND RADIO COMPANY LLC"},"createdAt":"2022-09-20T00:33:58.134Z","id":"0384758"}]